HDL_codes/mux.v
module mux2x1 #(
    parameter DATA_WIDTH = 32
)(
    input  [DATA_WIDTH-1:0] a,
    input  [DATA_WIDTH-1:0] b,
    input                   sel,
    output [DATA_WIDTH-1:0] out
);

assign out = sel ? b : a;

endmodule

HDL_codes/buffer.v
module buffer #(
    parameter WIDTH = 32,
    parameter DEPTH = 8
) (
    input clk,
    input rst,
    input wr_en,
    input rd_en,
    input [WIDTH-1:0] din,
    output reg [WIDTH-1:0] dout
);

    reg [WIDTH-1:0] mem [0:DEPTH-1];
    reg [$clog2(DEPTH)-1:0] wr_ptr, rd_ptr;

    always @(posedge clk or posedge rst) begin
        if (rst) begin
            wr_ptr <= 0;
            rd_ptr <= 0;
            dout   <= 0;
        end else begin
            if (wr_en) begin
                mem[wr_ptr] <= din;
                wr_ptr <= wr_ptr + 1;
            end

            if (rd_en) begin
                dout <= mem[rd_ptr];
                rd_ptr <= rd_ptr + 1;
            end
        end
    end
endmodule

RTL/Delay_unit.v
module Delay_Unit #(
    parameter DATAWIDTH = 32,
    parameter DEPTH     = 4,
    parameter N         = 16
) (
    // generic inputs 
    input clk_i, rst_i,
    // input valid signal 
    input valid_i, stall_i,
    // output valid signal 
    output reg valid_o,
    // Input 
    input  [DATAWIDTH-1:0] a_i, b_i,
    output [DATAWIDTH-1:0] a_o, b_o
);

// State Machine 
localparam STAGE1 = 0, STAGE2 = 1, STAGE3 = 2;
// Counter Width 
localparam CWIDTH = $clog2(DEPTH + 1);

// Signal Declaration 
reg [DATAWIDTH-1:0] ReadBuffer;
reg [CWIDTH-1:0]     Counter;
reg [1:0]           State;

// Read and Write signals for Internal Buffers
reg wr_en_1, wr_en_2, read_en_1, read_en_2;
reg ctrl_1, ctrl_2, ctrl_3;

// Buffer Instanciation 
wire [DATAWIDTH-1:0] Buff_1_w, Buff_2_w;
wire [DATAWIDTH-1:0] Buff_1_r, Buff_2_r;
wire [DATAWIDTH-1:0] b_o_mux;

// Internal Buffers 
    buffer #(
        .WIDTH(DATAWIDTH),
        .DEPTH(DEPTH)
    ) buffer_1 (
        .clk(clk_i),
        .rst(rst_i),
        .wr_en(wr_en_1),
        .rd_en(read_en_1),
        .din(Buff_1_w),
        .dout(Buff_1_r)
    );

    buffer #(
        .WIDTH(DATAWIDTH),
        .DEPTH(DEPTH)
    ) buffer_2 (
        .clk(clk_i),
        .rst(rst_i),
        .wr_en(wr_en_2),
        .rd_en(read_en_2),
        .din(Buff_2_w),
        .dout(Buff_2_r)
    );

// Input to Buffer MUX
    mux2x1 mux1 (
        .a(a_i),
        .b(b_i),
        .sel(ctrl_1),
        .out(Buff_1_w)
    );

    mux2x1 mux2 (
        .a(b_i),
        .b(a_i),
        .sel(ctrl_1),
        .out(Buff_2_w)
    );

// Output from Buffer MUX
    mux2x1 mux3 (
        .a(Buff_1_r),
        .b(Buff_2_r),
        .sel(ctrl_2),
        .out(a_o)
    );

    mux2x1 mux4 (
        .a(Buff_2_r),
        .b(Buff_1_r),
        .sel(ctrl_2),
        .out(b_o_mux)
    );

    mux2x1 mux5 (
        .a(b_o_mux),
        .b(ReadBuffer),
        .sel(ctrl_3),
        .out(b_o)
    );

    // Logic controll 
    always @(posedge clk_i or posedge rst_i) begin
        if (rst_i) begin 
            Counter <= 1;
            State   <= STAGE1;
            ctrl_2  <= 0;
            ctrl_3  <= 0;
            valid_o <= 0;
        end else begin 
            // pipeline stall and latch
            if (!stall_i) begin 

            if (valid_i) begin 
                Counter <= Counter + 1;
                case (State)
                    STAGE1: begin
                        // Out Mux Config
                        ctrl_2 <= 0;
                        ctrl_3 <= 0;
                        // State Change Logic
                        if (ChangeState) begin 
                            State   <= STAGE2;
                            Counter <= 1;
                        end 
                    end 
                    STAGE2: begin
                        ctrl_2     <= 0;
                        ctrl_3     <= 1;
                        ReadBuffer <= a_i;
                        if (ChangeState) begin 
                            State   <= STAGE3;
                            Counter <= 1;
                        end 
                        // Valid Output 
                        valid_o <= 1;
                    end
                    STAGE3: begin 
                        ctrl_2 <= 1;
                        ctrl_3 <= 0;
                        if (ChangeState) begin 
                            State   <= STAGE2;
                            Counter <= 1;
                        end 
                        // Valid Output 
                        valid_o <= 1;
                    end 
                endcase
            end else 
                valid_o <= 0;
            // Everything else is to be latched unless reset 
            end else 
                valid_o <= 0;
        end  
    end

    // Combinational control logic
    always @(*) begin 
        if (valid_i && !stall_i) begin 
            case (State) 
                STAGE1: begin
                    wr_en_1 = 1;
                    wr_en_2 = 1;
                    ctrl_1  = 0;
                    read_en_1 = 0;
                    read_en_2 = 0;
                end 

                STAGE2: begin 
                    wr_en_1 = 1;
                    wr_en_2 = 0;
                    ctrl_1  = 1;
                    read_en_1 = 1;
                    read_en_2 = 0;
                end 

                STAGE3: begin
                    wr_en_1 = 1;
                    wr_en_2 = 1;
                    ctrl_1  = 0;
                    read_en_1 = 1;
                    read_en_2 = 1;
                end
            endcase
        end else begin 
                wr_en_1   = 0;
                wr_en_2   = 0;
                read_en_1 = 0;
                read_en_2 = 0;
                ctrl_1    = 0;
        end
    end 

    // State Change Flag 
    wire ChangeState = (Counter == DEPTH/4);
    
endmodule

Verif/DelayUnit/tb_delay_unit.v
`timescale 1ns/1ps

module tb_Delay_Unit;

    // ============================================================
    // Parameters
    // ============================================================
    parameter DATAWIDTH = 32;
    parameter DEPTH     = 8;
    parameter N         = 16;

    // ============================================================
    // DUT Signals
    // ============================================================
    reg clk_i;
    reg rst_i;
    reg valid_i;

    reg  [DATAWIDTH-1:0] a_i, b_i;
    wire [DATAWIDTH-1:0] a_o, b_o;
    wire valid_o;
    reg stall;

    // ============================================================
    // Instantiate DUT
    // ============================================================
    Delay_Unit #(
        .DATAWIDTH(DATAWIDTH),
        .DEPTH(DEPTH),
        .N(N)
    ) dut (
        .clk_i(clk_i),
        .rst_i(rst_i),
        .stall_i(stall),
        .valid_i(valid_i),
        .valid_o(valid_o),
        .a_i(a_i),
        .b_i(b_i),
        .a_o(a_o),
        .b_o(b_o)
    );

    // ============================================================
    // Clock Generation (10ns period)
    // ============================================================
    always #5 clk_i = ~clk_i;

    // ============================================================
    // Stimulus
    // ============================================================
    integer i;

    initial begin
        // Init
        clk_i   = 0;
        rst_i   = 1;
        valid_i = 0;
        a_i     = 0;
        b_i     = 0;
        stall   = 0;

        // Reset
        #20;
        rst_i = 0;
        stall = 0;

        // Start streaming
        #10;
        valid_i = 1;

        // Apply data stream
        for (i = 0; i < 32; i = i + 1) begin
            @(posedge clk_i);
            a_i <= i;
            b_i <= i + 100;
        end

        // Stop input
        @(posedge clk_i);
        valid_i <= 0;

        // Wait some cycles
        repeat (10) @(posedge clk_i);

        $finish;
    end

    // ============================================================
    // Waveform Dump (GTKWave)
    // ============================================================
    initial begin
        $dumpfile("tb_delay_unit.vcd");
        $dumpvars(0, tb_Delay_Unit);

        // Dump DUT internals (VERY useful)
        $dumpvars(0, tb_Delay_Unit.dut);
        $dumpvars(0, tb_Delay_Unit.dut.State);
        $dumpvars(0, tb_Delay_Unit.dut.Counter);
    end

    // ============================================================
    // Monitor
    // ============================================================
    initial begin
        $display("Time\tvalid_i\ta_i\tb_i\t|\ta_o\tb_o\tvalid_o");
        $monitor("%0t\t%b\t%0d\t%0d\t|\t%0d\t%0d\t%b",
                 $time, valid_i, a_i, b_i, a_o, b_o, valid_o);
    end

endmodule

Verif/DelayUnit/tb_delay_unit.vcd
$date
	Sun Apr  5 23:56:16 2026
$end
$version
	Icarus Verilog
$end
$timescale
	1ps
$end
$scope module tb_Delay_Unit $end
$var wire 1 ! valid_o $end
$var wire 32 " b_o [31:0] $end
$var wire 32 # a_o [31:0] $end
$var reg 32 $ a_i [31:0] $end
$var reg 32 % b_i [31:0] $end
$var reg 1 & clk_i $end
$var reg 1 ' rst_i $end
$var reg 1 ( stall $end
$var reg 1 ) valid_i $end
$var integer 32 * i [31:0] $end
$scope module dut $end
$var wire 32 + a_i [31:0] $end
$var wire 32 , b_i [31:0] $end
$var wire 1 & clk_i $end
$var wire 1 ' rst_i $end
$var wire 1 ( stall_i $end
$var wire 1 ) valid_i $end
$var wire 32 - b_o_mux [31:0] $end
$var wire 32 . b_o [31:0] $end
$var wire 32 / a_o [31:0] $end
$var wire 1 0 ChangeState $end
$var wire 32 1 Buff_2_w [31:0] $end
$var wire 32 2 Buff_2_r [31:0] $end
$var wire 32 3 Buff_1_w [31:0] $end
$var wire 32 4 Buff_1_r [31:0] $end
$var reg 4 5 Counter [3:0] $end
$var reg 32 6 ReadBuffer [31:0] $end
$var reg 2 7 State [1:0] $end
$var reg 1 8 ctrl_1 $end
$var reg 1 9 ctrl_2 $end
$var reg 1 : ctrl_3 $end
$var reg 1 ; read_en_1 $end
$var reg 1 < read_en_2 $end
$var reg 1 ! valid_o $end
$var reg 1 = wr_en_1 $end
$var reg 1 > wr_en_2 $end
$scope module buffer_1 $end
$var wire 1 & clk $end
$var wire 1 ; rd_en $end
$var wire 1 ' rst $end
$var wire 1 = wr_en $end
$var wire 32 ? din [31:0] $end
$var reg 32 @ dout [31:0] $end
$var reg 3 A rd_ptr [2:0] $end
$var reg 3 B wr_ptr [2:0] $end
$upscope $end
$scope module buffer_2 $end
$var wire 1 & clk $end
$var wire 1 < rd_en $end
$var wire 1 ' rst $end
$var wire 1 > wr_en $end
$var wire 32 C din [31:0] $end
$var reg 32 D dout [31:0] $end
$var reg 3 E rd_ptr [2:0] $end
$var reg 3 F wr_ptr [2:0] $end
$upscope $end
$scope module mux1 $end
$var wire 32 G a [31:0] $end
$var wire 32 H b [31:0] $end
$var wire 1 8 sel $end
$var wire 32 I out [31:0] $end
$upscope $end
$scope module mux2 $end
$var wire 32 J a [31:0] $end
$var wire 32 K b [31:0] $end
$var wire 1 8 sel $end
$var wire 32 L out [31:0] $end
$upscope $end
$scope module mux3 $end
$var wire 32 M a [31:0] $end
$var wire 32 N b [31:0] $end
$var wire 1 9 sel $end
$var wire 32 O out [31:0] $end
$upscope $end
$scope module mux4 $end
$var wire 32 P a [31:0] $end
$var wire 32 Q b [31:0] $end
$var wire 1 9 sel $end
$var wire 32 R out [31:0] $end
$upscope $end
$scope module mux5 $end
$var wire 32 S a [31:0] $end
$var wire 32 T b [31:0] $end
$var wire 1 : sel $end
$var wire 32 U out [31:0] $end
$upscope $end
$upscope $end
$upscope $end
$scope module tb_Delay_Unit $end
$scope module dut $end
$scope module buffer_1 $end
$upscope $end
$scope module buffer_2 $end
$upscope $end
$scope module mux1 $end
$upscope $end
$scope module mux2 $end
$upscope $end
$scope module mux3 $end
$upscope $end
$scope module mux4 $end
$upscope $end
$scope module mux5 $end
$upscope $end
$upscope $end
$upscope $end
$enddefinitions $end
#0
$dumpvars
b0 U
bx T
b0 S
b0 R
b0 Q
b0 P
b0 O
b0 N
b0 M
b0 L
b0 K
b0 J
b0 I
b0 H
b0 G
b0 F
b0 E
b0 D
b0 C
b0 B
b0 A
b0 @
b0 ?
0>
0=
0<
0;
0:
09
08
b0 7
bx 6
b1 5
b0 4
b0 3
b0 2
b0 1
00
b0 /
b0 .
b0 -
b0 ,
b0 +
bx *
0)
0(
1'
0&
b0 %
b0 $
b0 #
b0 "
0!
$end
#5000
1&
#10000
0&
#15000
1&
#20000
0&
0'
#25000
1&
#30000
1>
1=
0&
b0 *
1)
#35000
b1100100 1
b1100100 C
b1100100 L
b1 B
b1 F
10
b10 5
b1100100 %
b1100100 ,
b1100100 H
b1100100 J
b1 *
1&
#40000
0&
#45000
1;
18
0>
b1 1
b1 C
b1 L
b1100101 3
b1100101 ?
b1100101 I
b1 7
00
b1 5
b10 F
b10 B
b1100101 %
b1100101 ,
b1100101 H
b1100101 J
b1 $
b1 +
b1 G
b1 K
b10 *
1&
#50000
0&
#55000
b1 "
b1 .
b1 U
b1100110 3
b1100110 ?
b1100110 I
b10 1
b10 C
b10 L
b1 A
b11 B
1!
b1 6
b1 T
1:
10
b10 5
b1100110 %
b1100110 ,
b1100110 H
b1100110 J
b10 $
b10 +
b10 G
b10 K
b11 *
1&
#60000
0&
#65000
1<
08
1>
b10 "
b10 .
b10 U
b11 3
b11 ?
b11 I
b1100111 1
b1100111 C
b1100111 L
b10 7
b10 6
b10 T
00
b1 5
b10 A
b100 B
b1100111 %
b1100111 ,
b1100111 H
b1100111 J
b11 $
b11 +
b11 G
b11 K
b100 *
1&
#70000
0&
#75000
b1100101 "
b1100101 .
b1100101 U
b1100101 -
b1100101 R
b1100101 S
b1101000 1
b1101000 C
b1101000 L
b100 3
b100 ?
b100 I
b11 A
b1100101 4
b1100101 @
b1100101 M
b1100101 Q
b101 B
b1 E
b11 F
0:
19
10
b10 5
b1101000 %
b1101000 ,
b1101000 H
b1101000 J
b100 $
b100 +
b100 G
b100 K
b101 *
1&
#80000
0&
#85000
b1100110 "
b1100110 .
b1100110 U
0<
18
0>
b1100100 #
b1100100 /
b1100100 O
b1100110 -
b1100110 R
b1100110 S
b101 1
b101 C
b101 L
b1101001 3
b1101001 ?
b1101001 I
b1 7
00
b1 5
b10 E
b1100100 2
b1100100 D
b1100100 N
b1100100 P
b100 F
b100 A
b1100110 4
b1100110 @
b1100110 M
b1100110 Q
b110 B
b1101001 %
b1101001 ,
b1101001 H
b1101001 J
b101 $
b101 +
b101 G
b101 K
b110 *
1&
#90000
0&
#95000
b101 "
b101 .
b101 U
b11 #
b11 /
b11 O
b1100100 -
b1100100 R
b1100100 S
b1101010 3
b1101010 ?
b1101010 I
b110 1
b110 C
b110 L
b101 A
b11 4
b11 @
b11 M
b11 Q
b111 B
b101 6
b101 T
1:
09
10
b10 5
b1101010 %
b1101010 ,
b1101010 H
b1101010 J
b110 $
b110 +
b110 G
b110 K
b111 *
1&
#100000
0&
#105000
1<
08
1>
b110 "
b110 .
b110 U
b100 #
b100 /
b100 O
b111 3
b111 ?
b111 I
b1101011 1
b1101011 C
b1101011 L
b10 7
b110 6
b110 T
00
b1 5
b110 A
b100 4
b100 @
b100 M
b100 Q
b0 B
b1101011 %
b1101011 ,
b1101011 H
b1101011 J
b111 $
b111 +
b111 G
b111 K
b1000 *
1&
#110000
0&
#115000
b1101001 "
b1101001 .
b1101001 U
b1100111 #
b1100111 /
b1100111 O
b1101001 -
b1101001 R
b1101001 S
b1101100 1
b1101100 C
b1101100 L
b1000 3
b1000 ?
b1000 I
b111 A
b1101001 4
b1101001 @
b1101001 M
b1101001 Q
b1 B
b11 E
b1100111 2
b1100111 D
b1100111 N
b1100111 P
b101 F
0:
19
10
b10 5
b1101100 %
b1101100 ,
b1101100 H
b1101100 J
b1000 $
b1000 +
b1000 G
b1000 K
b1001 *
1&
#120000
0&
#125000
b1101010 "
b1101010 .
b1101010 U
0<
18
0>
b1101000 #
b1101000 /
b1101000 O
b1101010 -
b1101010 R
b1101010 S
b1001 1
b1001 C
b1001 L
b1101101 3
b1101101 ?
b1101101 I
b1 7
00
b1 5
b100 E
b1101000 2
b1101000 D
b1101000 N
b1101000 P
b110 F
b0 A
b1101010 4
b1101010 @
b1101010 M
b1101010 Q
b10 B
b1101101 %
b1101101 ,
b1101101 H
b1101101 J
b1001 $
b1001 +
b1001 G
b1001 K
b1010 *
1&
#130000
0&
#135000
b1001 "
b1001 .
b1001 U
b111 #
b111 /
b111 O
b1101000 -
b1101000 R
b1101000 S
b1101110 3
b1101110 ?
b1101110 I
b1010 1
b1010 C
b1010 L
b1 A
b111 4
b111 @
b111 M
b111 Q
b11 B
b1001 6
b1001 T
1:
09
10
b10 5
b1101110 %
b1101110 ,
b1101110 H
b1101110 J
b1010 $
b1010 +
b1010 G
b1010 K
b1011 *
1&
#140000
0&
#145000
1<
08
1>
b1010 "
b1010 .
b1010 U
b1000 #
b1000 /
b1000 O
b1011 3
b1011 ?
b1011 I
b1101111 1
b1101111 C
b1101111 L
b10 7
b1010 6
b1010 T
00
b1 5
b10 A
b1000 4
b1000 @
b1000 M
b1000 Q
b100 B
b1101111 %
b1101111 ,
b1101111 H
b1101111 J
b1011 $
b1011 +
b1011 G
b1011 K
b1100 *
1&
#150000
0&
#155000
b1101101 "
b1101101 .
b1101101 U
b1101011 #
b1101011 /
b1101011 O
b1101101 -
b1101101 R
b1101101 S
b1110000 1
b1110000 C
b1110000 L
b1100 3
b1100 ?
b1100 I
b11 A
b1101101 4
b1101101 @
b1101101 M
b1101101 Q
b101 B
b101 E
b1101011 2
b1101011 D
b1101011 N
b1101011 P
b111 F
0:
19
10
b10 5
b1110000 %
b1110000 ,
b1110000 H
b1110000 J
b1100 $
b1100 +
b1100 G
b1100 K
b1101 *
1&
#160000
0&
#165000
b1101110 "
b1101110 .
b1101110 U
0<
18
0>
b1101100 #
b1101100 /
b1101100 O
b1101110 -
b1101110 R
b1101110 S
b1101 1
b1101 C
b1101 L
b1110001 3
b1110001 ?
b1110001 I
b1 7
00
b1 5
b110 E
b1101100 2
b1101100 D
b1101100 N
b1101100 P
b0 F
b100 A
b1101110 4
b1101110 @
b1101110 M
b1101110 Q
b110 B
b1110001 %
b1110001 ,
b1110001 H
b1110001 J
b1101 $
b1101 +
b1101 G
b1101 K
b1110 *
1&
#170000
0&
#175000
b1101 "
b1101 .
b1101 U
b1011 #
b1011 /
b1011 O
b1101100 -
b1101100 R
b1101100 S
b1110010 3
b1110010 ?
b1110010 I
b1110 1
b1110 C
b1110 L
b101 A
b1011 4
b1011 @
b1011 M
b1011 Q
b111 B
b1101 6
b1101 T
1:
09
10
b10 5
b1110010 %
b1110010 ,
b1110010 H
b1110010 J
b1110 $
b1110 +
b1110 G
b1110 K
b1111 *
1&
#180000
0&
#185000
1<
08
1>
b1110 "
b1110 .
b1110 U
b1100 #
b1100 /
b1100 O
b1111 3
b1111 ?
b1111 I
b1110011 1
b1110011 C
b1110011 L
b10 7
b1110 6
b1110 T
00
b1 5
b110 A
b1100 4
b1100 @
b1100 M
b1100 Q
b0 B
b1110011 %
b1110011 ,
b1110011 H
b1110011 J
b1111 $
b1111 +
b1111 G
b1111 K
b10000 *
1&
#190000
0&
#195000
b1110001 "
b1110001 .
b1110001 U
b1101111 #
b1101111 /
b1101111 O
b1110001 -
b1110001 R
b1110001 S
b1110100 1
b1110100 C
b1110100 L
b10000 3
b10000 ?
b10000 I
b111 A
b1110001 4
b1110001 @
b1110001 M
b1110001 Q
b1 B
b111 E
b1101111 2
b1101111 D
b1101111 N
b1101111 P
b1 F
0:
19
10
b10 5
b1110100 %
b1110100 ,
b1110100 H
b1110100 J
b10000 $
b10000 +
b10000 G
b10000 K
b10001 *
1&
#200000
0&
#205000
b1110010 "
b1110010 .
b1110010 U
0<
18
0>
b1110000 #
b1110000 /
b1110000 O
b1110010 -
b1110010 R
b1110010 S
b10001 1
b10001 C
b10001 L
b1110101 3
b1110101 ?
b1110101 I
b1 7
00
b1 5
b0 E
b1110000 2
b1110000 D
b1110000 N
b1110000 P
b10 F
b0 A
b1110010 4
b1110010 @
b1110010 M
b1110010 Q
b10 B
b1110101 %
b1110101 ,
b1110101 H
b1110101 J
b10001 $
b10001 +
b10001 G
b10001 K
b10010 *
1&
#210000
0&
#215000
b10001 "
b10001 .
b10001 U
b1111 #
b1111 /
b1111 O
b1110000 -
b1110000 R
b1110000 S
b1110110 3
b1110110 ?
b1110110 I
b10010 1
b10010 C
b10010 L
b1 A
b1111 4
b1111 @
b1111 M
b1111 Q
b11 B
b10001 6
b10001 T
1:
09
10
b10 5
b1110110 %
b1110110 ,
b1110110 H
b1110110 J
b10010 $
b10010 +
b10010 G
b10010 K
b10011 *
1&
#220000
0&
#225000
1<
08
1>
b10010 "
b10010 .
b10010 U
b10000 #
b10000 /
b10000 O
b10011 3
b10011 ?
b10011 I
b1110111 1
b1110111 C
b1110111 L
b10 7
b10010 6
b10010 T
00
b1 5
b10 A
b10000 4
b10000 @
b10000 M
b10000 Q
b100 B
b1110111 %
b1110111 ,
b1110111 H
b1110111 J
b10011 $
b10011 +
b10011 G
b10011 K
b10100 *
1&
#230000
0&
#235000
b1110101 "
b1110101 .
b1110101 U
b1110011 #
b1110011 /
b1110011 O
b1110101 -
b1110101 R
b1110101 S
b1111000 1
b1111000 C
b1111000 L
b10100 3
b10100 ?
b10100 I
b11 A
b1110101 4
b1110101 @
b1110101 M
b1110101 Q
b101 B
b1 E
b1110011 2
b1110011 D
b1110011 N
b1110011 P
b11 F
0:
19
10
b10 5
b1111000 %
b1111000 ,
b1111000 H
b1111000 J
b10100 $
b10100 +
b10100 G
b10100 K
b10101 *
1&
#240000
0&
#245000
b1110110 "
b1110110 .
b1110110 U
0<
18
0>
b1110100 #
b1110100 /
b1110100 O
b1110110 -
b1110110 R
b1110110 S
b10101 1
b10101 C
b10101 L
b1111001 3
b1111001 ?
b1111001 I
b1 7
00
b1 5
b10 E
b1110100 2
b1110100 D
b1110100 N
b1110100 P
b100 F
b100 A
b1110110 4
b1110110 @
b1110110 M
b1110110 Q
b110 B
b1111001 %
b1111001 ,
b1111001 H
b1111001 J
b10101 $
b10101 +
b10101 G
b10101 K
b10110 *
1&
#250000
0&
#255000
b10101 "
b10101 .
b10101 U
b10011 #
b10011 /
b10011 O
b1110100 -
b1110100 R
b1110100 S
b1111010 3
b1111010 ?
b1111010 I
b10110 1
b10110 C
b10110 L
b101 A
b10011 4
b10011 @
b10011 M
b10011 Q
b111 B
b10101 6
b10101 T
1:
09
10
b10 5
b1111010 %
b1111010 ,
b1111010 H
b1111010 J
b10110 $
b10110 +
b10110 G
b10110 K
b10111 *
1&
#260000
0&
#265000
1<
08
1>
b10110 "
b10110 .
b10110 U
b10100 #
b10100 /
b10100 O
b10111 3
b10111 ?
b10111 I
b1111011 1
b1111011 C
b1111011 L
b10 7
b10110 6
b10110 T
00
b1 5
b110 A
b10100 4
b10100 @
b10100 M
b10100 Q
b0 B
b1111011 %
b1111011 ,
b1111011 H
b1111011 J
b10111 $
b10111 +
b10111 G
b10111 K
b11000 *
1&
#270000
0&
#275000
b1111001 "
b1111001 .
b1111001 U
b1110111 #
b1110111 /
b1110111 O
b1111001 -
b1111001 R
b1111001 S
b1111100 1
b1111100 C
b1111100 L
b11000 3
b11000 ?
b11000 I
b111 A
b1111001 4
b1111001 @
b1111001 M
b1111001 Q
b1 B
b11 E
b1110111 2
b1110111 D
b1110111 N
b1110111 P
b101 F
0:
19
10
b10 5
b1111100 %
b1111100 ,
b1111100 H
b1111100 J
b11000 $
b11000 +
b11000 G
b11000 K
b11001 *
1&
#280000
0&
#285000
b1111010 "
b1111010 .
b1111010 U
0<
18
0>
b1111000 #
b1111000 /
b1111000 O
b1111010 -
b1111010 R
b1111010 S
b11001 1
b11001 C
b11001 L
b1111101 3
b1111101 ?
b1111101 I
b1 7
00
b1 5
b100 E
b1111000 2
b1111000 D
b1111000 N
b1111000 P
b110 F
b0 A
b1111010 4
b1111010 @
b1111010 M
b1111010 Q
b10 B
b1111101 %
b1111101 ,
b1111101 H
b1111101 J
b11001 $
b11001 +
b11001 G
b11001 K
b11010 *
1&
#290000
0&
#295000
b11001 "
b11001 .
b11001 U
b10111 #
b10111 /
b10111 O
b1111000 -
b1111000 R
b1111000 S
b1111110 3
b1111110 ?
b1111110 I
b11010 1
b11010 C
b11010 L
b1 A
b10111 4
b10111 @
b10111 M
b10111 Q
b11 B
b11001 6
b11001 T
1:
09
10
b10 5
b1111110 %
b1111110 ,
b1111110 H
b1111110 J
b11010 $
b11010 +
b11010 G
b11010 K
b11011 *
1&
#300000
0&
#305000
1<
08
1>
b11010 "
b11010 .
b11010 U
b11000 #
b11000 /
b11000 O
b11011 3
b11011 ?
b11011 I
b1111111 1
b1111111 C
b1111111 L
b10 7
b11010 6
b11010 T
00
b1 5
b10 A
b11000 4
b11000 @
b11000 M
b11000 Q
b100 B
b1111111 %
b1111111 ,
b1111111 H
b1111111 J
b11011 $
b11011 +
b11011 G
b11011 K
b11100 *
1&
#310000
0&
#315000
b1111101 "
b1111101 .
b1111101 U
b1111011 #
b1111011 /
b1111011 O
b1111101 -
b1111101 R
b1111101 S
b10000000 1
b10000000 C
b10000000 L
b11100 3
b11100 ?
b11100 I
b11 A
b1111101 4
b1111101 @
b1111101 M
b1111101 Q
b101 B
b101 E
b1111011 2
b1111011 D
b1111011 N
b1111011 P
b111 F
0:
19
10
b10 5
b10000000 %
b10000000 ,
b10000000 H
b10000000 J
b11100 $
b11100 +
b11100 G
b11100 K
b11101 *
1&
#320000
0&
#325000
b1111110 "
b1111110 .
b1111110 U
0<
18
0>
b1111100 #
b1111100 /
b1111100 O
b1111110 -
b1111110 R
b1111110 S
b11101 1
b11101 C
b11101 L
b10000001 3
b10000001 ?
b10000001 I
b1 7
00
b1 5
b110 E
b1111100 2
b1111100 D
b1111100 N
b1111100 P
b0 F
b100 A
b1111110 4
b1111110 @
b1111110 M
b1111110 Q
b110 B
b10000001 %
b10000001 ,
b10000001 H
b10000001 J
b11101 $
b11101 +
b11101 G
b11101 K
b11110 *
1&
#330000
0&
#335000
b11101 "
b11101 .
b11101 U
b11011 #
b11011 /
b11011 O
b1111100 -
b1111100 R
b1111100 S
b10000010 3
b10000010 ?
b10000010 I
b11110 1
b11110 C
b11110 L
b101 A
b11011 4
b11011 @
b11011 M
b11011 Q
b111 B
b11101 6
b11101 T
1:
09
10
b10 5
b10000010 %
b10000010 ,
b10000010 H
b10000010 J
b11110 $
b11110 +
b11110 G
b11110 K
b11111 *
1&
#340000
0&
#345000
1<
08
1>
b11110 "
b11110 .
b11110 U
b11100 #
b11100 /
b11100 O
b11111 3
b11111 ?
b11111 I
b10000011 1
b10000011 C
b10000011 L
b10 7
b11110 6
b11110 T
00
b1 5
b110 A
b11100 4
b11100 @
b11100 M
b11100 Q
b0 B
b10000011 %
b10000011 ,
b10000011 H
b10000011 J
b11111 $
b11111 +
b11111 G
b11111 K
b100000 *
1&
#350000
0&
#355000
b10000001 "
b10000001 .
b10000001 U
b1111111 #
b1111111 /
b1111111 O
b10000001 -
b10000001 R
b10000001 S
0<
0;
0>
0=
b111 A
b10000001 4
b10000001 @
b10000001 M
b10000001 Q
b1 B
b111 E
b1111111 2
b1111111 D
b1111111 N
b1111111 P
b1 F
0:
19
10
b10 5
0)
1&
#360000
0&
#365000
0!
1&
