HDL_codes/MontgomeryReductionUnit.v
module MontgomeryReductionUnit #(
    parameter Q_WIDTH = 14,
    parameter Q = 12289,
    parameter Q_INV = 12287
)(
    input clk,
    input rst,

    input start,
    input stall,
    input [Q_WIDTH-1:0] b_bar,
    input [Q_WIDTH-1:0] w_bar,

    output reg [Q_WIDTH-1:0] c_bar
);

    localparam R_MASK = (1 << Q_WIDTH) - 1;

    // Stage 1: Multiply
    reg [2*Q_WIDTH-1:0] x_s1;
    reg valid_s1;

    // Stage 2: Compute s
    reg [Q_WIDTH-1:0] s_s2;
    reg [2*Q_WIDTH-1:0] x_s2;
    reg valid_s2;

    // Stage 3: Compute t
    reg [2*Q_WIDTH-1:0] t_s3;
    reg valid_s3;

    always @(posedge clk or posedge rst) begin
        if (rst) begin
            valid_s1 <= 0;
            valid_s2 <= 0;
            valid_s3 <= 0;
            x_s1 <= 0;
            x_s2 <= 0;
            s_s2 <= 0;
            t_s3 <= 0;
            c_bar <= 0;
        end 
        else if (!stall) begin

            // Stage 1
            valid_s1 <= start;
            if (start)
                x_s1 <= b_bar * w_bar;

            // Stage 2
            valid_s2 <= valid_s1;
            if (valid_s1) begin
                s_s2 <= (x_s1 * Q_INV) & R_MASK;
                x_s2 <= x_s1;  // forward x
            end

            // Stage 3
            valid_s3 <= valid_s2;
            if (valid_s2)
                t_s3 <= x_s2 + s_s2 * Q;

            // Stage 4
            if (valid_s3) begin
                // shift + subtract
                if ((t_s3 >> Q_WIDTH) >= Q)
                    c_bar <= (t_s3 >> Q_WIDTH) - Q;
                else
                    c_bar <= (t_s3 >> Q_WIDTH);
            end

        end
    end

endmodule

HDL_codes/FromMont.v

module FromMontgomeryConverter #(
    parameter Q_WIDTH = 14,
    parameter Q = 12289
)(
    input clk,
    input rst,
    input [Q_WIDTH-1:0] c_bar,
    input start,
    input stall,
    output wire [Q_WIDTH-1:0] c
);

    wire [Q_WIDTH-1:0] c_wire;

    MontgomeryReductionUnit #(
        .Q_WIDTH(Q_WIDTH),
        .Q(Q)
    ) mont_inv (
        .clk(clk),
        .rst(rst),
        .start(start),
        .stall(stall),
        .b_bar(c_bar),
        .w_bar({{Q_WIDTH-1{1'b0}},1'b1}),
        .c_bar(c_wire)
    );

    assign c = c_wire;

endmodule

HDL_codes/ToMont.v
module ToMontgomeryConverter #(
    parameter Q_WIDTH = 14,
    parameter Q = 12289,
  parameter R2_MOD_Q = 6829   // R^2 mod q
)(
    input clk,
    input rst,
    input [Q_WIDTH-1:0] a,
    input [Q_WIDTH-1:0] b,
    input start,
    input stall,
    output wire [Q_WIDTH-1:0] a_bar,
    output wire [Q_WIDTH-1:0] b_bar
);

    // Wires for Montgomery outputs
    wire [Q_WIDTH-1:0] a_bar_wire;
    wire [Q_WIDTH-1:0] b_bar_wire;

    // Instantiate Montgomery Reduction Units
    MontgomeryReductionUnit #(
        .Q_WIDTH(Q_WIDTH),
        .Q(Q)
    ) mont_a (
        .clk(clk),
        .rst(rst),
        .start(start),
        .stall(stall),
        .b_bar(a),
        .w_bar(R2_MOD_Q[Q_WIDTH-1:0]),
        .c_bar(a_bar_wire)
    );

    MontgomeryReductionUnit #(
        .Q_WIDTH(Q_WIDTH),
        .Q(Q)
    ) mont_b (
        .clk(clk),
        .rst(rst),
        .start(start),
        .stall(stall),
        .b_bar(b),
        .w_bar(R2_MOD_Q[Q_WIDTH-1:0]),
        .c_bar(b_bar_wire)
    );
  
    assign a_bar = a_bar_wire;
    assign b_bar = b_bar_wire;
endmodule

verif/tb_full_montgomery_pipeline.v
module tb_full_montgomery_pipeline;

    parameter Q = 12289;
    parameter Q_WIDTH = 14;
    parameter R = (1 << Q_WIDTH);
    parameter Q_INV = 97;
    //parameter R_INV = 9216;
    parameter R2_MOD_Q = 6829;

    reg clk;
    reg rst;
    reg start;
    reg stall;

    reg [Q_WIDTH-1:0] a, b;

    wire [Q_WIDTH-1:0] a_bar, b_bar;
    wire [Q_WIDTH-1:0] c_bar;
    wire [Q_WIDTH-1:0] c;

    // DUTs
    ToMontgomeryConverter form (
        .clk(clk),
        .rst(rst),
        .a(a),
        .b(b),
        .start(start),
        .stall(stall),
        .a_bar(a_bar),
        .b_bar(b_bar)
    );

    MontgomeryReductionUnit mult (
        .clk(clk),
        .rst(rst),
        .start(start),
        .stall(stall),
        .b_bar(a_bar),
        .w_bar(b_bar),
        .c_bar(c_bar)
    );

    FromMontgomeryConverter inv (
        .clk(clk),
        .rst(rst),
        .start(start),
        .stall(stall),
        .c_bar(c_bar),
        .c(c)
    );

    // Clock
    always #5 clk = ~clk;

    // Reference function
    function [Q_WIDTH-1:0] mod_mul;
        input [Q_WIDTH-1:0] x, y;
        reg [2*Q_WIDTH-1:0] temp;
        begin
            temp = x * y;
            mod_mul = temp % Q;
        end
    endfunction

    integer i, j;
    reg [Q_WIDTH-1:0] expected_q [0:9];
    reg [Q_WIDTH-1:0] a_q [0:9];
    reg [Q_WIDTH-1:0] b_q [0:9];

    initial begin
    $dumpfile("full_pipeline.vcd");
    $dumpvars(0, tb_full_montgomery_pipeline);

    clk = 0;
    rst = 1;
    start = 0;
    stall = 0;
    #20;
    rst = 0;
    start = 1;

    for (i = 0; i < 10; i = i + 1) begin
        @(posedge clk);
        a = $urandom % Q;
        b = $urandom % Q;
        expected_q[i] = mod_mul(a, b);
        a_q[i] = a;
        b_q[i] = b;
    end

    repeat (3) @(posedge clk);

    for (j = 0; j < 10; j = j + 1) begin
        if (expected_q[j] !== c) begin
            $display("FAIL: a=%d b=%d Expected=%d Got=%d",
                      a_q[j], b_q[j], expected_q[j], c);
        end else begin
            $display("time=%0t PASS: a=%d b=%d result=%d",
                      $time, a_q[j], b_q[j], c);
        end
        @(posedge clk);
    end

    #100;
    $finish;
    end

endmodule

verif/full_pipeline.vcd
$date
	Fri Apr  3 17:07:02 2026
$end
$version
	Icarus Verilog
$end
$timescale
	1s
$end
$scope module tb_full_montgomery_pipeline $end
$var wire 14 ! c_bar [13:0] $end
$var wire 14 " c [13:0] $end
$var wire 14 # b_bar [13:0] $end
$var wire 14 $ a_bar [13:0] $end
$var parameter 32 % Q $end
$var parameter 32 & Q_INV $end
$var parameter 32 ' Q_WIDTH $end
$var parameter 46 ( R $end
$var parameter 32 ) R2_MOD_Q $end
$var reg 14 * a [13:0] $end
$var reg 14 + b [13:0] $end
$var reg 1 , clk $end
$var reg 1 - rst $end
$var reg 1 . stall $end
$var reg 1 / start $end
$var integer 32 0 i [31:0] $end
$var integer 32 1 j [31:0] $end
$scope function mod_mul $end
$var reg 28 2 temp [27:0] $end
$var reg 14 3 x [13:0] $end
$var reg 14 4 y [13:0] $end
$upscope $end
$scope module form $end
$var wire 14 5 a [13:0] $end
$var wire 14 6 a_bar [13:0] $end
$var wire 14 7 b [13:0] $end
$var wire 14 8 b_bar [13:0] $end
$var wire 1 , clk $end
$var wire 1 - rst $end
$var wire 1 . stall $end
$var wire 1 / start $end
$var wire 14 9 b_bar_wire [13:0] $end
$var wire 14 : a_bar_wire [13:0] $end
$var parameter 32 ; Q $end
$var parameter 32 < Q_WIDTH $end
$var parameter 32 = R2_MOD_Q $end
$scope module mont_a $end
$var wire 14 > b_bar [13:0] $end
$var wire 1 , clk $end
$var wire 1 - rst $end
$var wire 1 . stall $end
$var wire 1 / start $end
$var wire 14 ? w_bar [13:0] $end
$var parameter 32 @ Q $end
$var parameter 32 A Q_INV $end
$var parameter 32 B Q_WIDTH $end
$var parameter 47 C R_MASK $end
$var reg 14 D c_bar [13:0] $end
$var reg 14 E s_s2 [13:0] $end
$var reg 28 F t_s3 [27:0] $end
$var reg 1 G valid_s1 $end
$var reg 1 H valid_s2 $end
$var reg 1 I valid_s3 $end
$var reg 28 J x_s1 [27:0] $end
$var reg 28 K x_s2 [27:0] $end
$upscope $end
$scope module mont_b $end
$var wire 14 L b_bar [13:0] $end
$var wire 1 , clk $end
$var wire 1 - rst $end
$var wire 1 . stall $end
$var wire 1 / start $end
$var wire 14 M w_bar [13:0] $end
$var parameter 32 N Q $end
$var parameter 32 O Q_INV $end
$var parameter 32 P Q_WIDTH $end
$var parameter 47 Q R_MASK $end
$var reg 14 R c_bar [13:0] $end
$var reg 14 S s_s2 [13:0] $end
$var reg 28 T t_s3 [27:0] $end
$var reg 1 U valid_s1 $end
$var reg 1 V valid_s2 $end
$var reg 1 W valid_s3 $end
$var reg 28 X x_s1 [27:0] $end
$var reg 28 Y x_s2 [27:0] $end
$upscope $end
$upscope $end
$scope module inv $end
$var wire 14 Z c [13:0] $end
$var wire 1 , clk $end
$var wire 1 - rst $end
$var wire 1 . stall $end
$var wire 1 / start $end
$var wire 14 [ c_wire [13:0] $end
$var wire 14 \ c_bar [13:0] $end
$var parameter 32 ] Q $end
$var parameter 32 ^ Q_WIDTH $end
$scope module mont_inv $end
$var wire 1 , clk $end
$var wire 1 - rst $end
$var wire 1 . stall $end
$var wire 1 / start $end
$var wire 14 _ w_bar [13:0] $end
$var wire 14 ` b_bar [13:0] $end
$var parameter 32 a Q $end
$var parameter 32 b Q_INV $end
$var parameter 32 c Q_WIDTH $end
$var parameter 47 d R_MASK $end
$var reg 14 e c_bar [13:0] $end
$var reg 14 f s_s2 [13:0] $end
$var reg 28 g t_s3 [27:0] $end
$var reg 1 h valid_s1 $end
$var reg 1 i valid_s2 $end
$var reg 1 j valid_s3 $end
$var reg 28 k x_s1 [27:0] $end
$var reg 28 l x_s2 [27:0] $end
$upscope $end
$upscope $end
$scope module mult $end
$var wire 14 m b_bar [13:0] $end
$var wire 1 , clk $end
$var wire 1 - rst $end
$var wire 1 . stall $end
$var wire 1 / start $end
$var wire 14 n w_bar [13:0] $end
$var parameter 32 o Q $end
$var parameter 32 p Q_INV $end
$var parameter 32 q Q_WIDTH $end
$var parameter 47 r R_MASK $end
$var reg 14 s c_bar [13:0] $end
$var reg 14 t s_s2 [13:0] $end
$var reg 28 u t_s3 [27:0] $end
$var reg 1 v valid_s1 $end
$var reg 1 w valid_s2 $end
$var reg 1 x valid_s3 $end
$var reg 28 y x_s1 [27:0] $end
$var reg 28 z x_s2 [27:0] $end
$upscope $end
$upscope $end
$enddefinitions $end
$comment Show the parameter values. $end
$dumpall
b11111111111111 r
b1110 q
b10111111111111 p
b11000000000001 o
b11111111111111 d
b1110 c
b10111111111111 b
b11000000000001 a
b1110 ^
b11000000000001 ]
b11111111111111 Q
b1110 P
b10111111111111 O
b11000000000001 N
b11111111111111 C
b1110 B
b10111111111111 A
b11000000000001 @
b1101010101101 =
b1110 <
b11000000000001 ;
b1101010101101 )
b100000000000000 (
b1110 '
b1100001 &
b11000000000001 %
$end
#0
$dumpvars
b0 z
b0 y
0x
0w
0v
b0 u
b0 t
b0 s
b0 n
b0 m
b0 l
b0 k
0j
0i
0h
b0 g
b0 f
b0 e
b0 `
b1 _
b0 \
b0 [
b0 Z
b0 Y
b0 X
0W
0V
0U
b0 T
b0 S
b0 R
b1101010101101 M
bx L
b0 K
b0 J
0I
0H
0G
b0 F
b0 E
b0 D
b1101010101101 ?
bx >
b0 :
b0 9
b0 8
bx 7
b0 6
bx 5
bx 4
bx 3
bx 2
bx 1
bx 0
0/
0.
1-
0,
bx +
bx *
b0 $
b0 #
b0 "
b0 !
$end
#5
1,
#10
0,
#15
1,
#20
0,
b0 0
1/
0-
#25
1h
1v
b11111111101011111011001011 X
1U
b10101110000010110011100101 J
1G
b1 0
b11111010001001010001111111 2
b1101000011001 3
b10011001010111 4
b10011001010111 +
b10011001010111 7
b10011001010111 L
b1101000011001 *
b1101000011001 5
b1101000011001 >
1,
#30
0,
#35
b10101110000010110011100101 K
b1100011011 E
1H
b1011100111100101100110000 J
b11111111101011111011001011 Y
b1000100110101 S
1V
b10111011001100110000101010 X
1w
1i
b10 0
b1100001110011101011100000 2
b110111110000 3
b1110000010010 4
b1110000010010 +
b1110000010010 7
b1110000010010 L
b110111110000 *
b110111110000 5
b110111110000 >
1,
#40
0,
#45
1j
1x
b111001110001100000000000000 T
1W
b10111011001100110000101010 Y
b1001111010110 S
b10001011111010101110011111 X
b11010011010100000000000000 F
1I
b1011100111100101100110000 K
b11010011010000 E
b100101001010100001010110001 J
b11 0
b11101001110101101000010111 2
b10110010010101 3
b1010011111011 4
b1010011111011 +
b1010011111011 7
b1010011111011 L
b10110010010101 *
b10110010010101 5
b10110010010101 >
1,
#50
0,
#55
b110100110101 $
b110100110101 6
b110100110101 m
b110100110101 :
b110100110101 D
b1011010110110000000000000000 F
b100101001010100001010110001 K
b10110101001111 E
b10010000101101011111110111 J
b1110011100011 #
b1110011100011 8
b1110011100011 n
b1110011100011 9
b1110011100011 R
b110101001010000000000000000 T
b10001011111010101110011111 Y
b10010001100001 S
b110001001011101111100 X
b100 0
b101000000000100000100 2
b1010110110011 3
b11101100 4
b11101100 +
b11101100 7
b11101100 L
b1010110110011 *
b1010110110011 5
b1010110110011 >
1,
#60
0,
#65
b1011111011000000111111111 y
b1101010010100 #
b1101010010100 8
b1101010010100 n
b1101010010100 9
b1101010010100 R
b1001000000100000000000000000 T
b110001001011101111100 Y
b10100010000100 S
b11000111101110101100110111 X
b10110101101100 $
b10110101101100 6
b10110101101100 m
b10110101101100 :
b10110101101100 D
b1101001001000100000000000000 F
b10010000101101011111110111 K
b11100000001001 E
b10110000101110100010000 J
b101 0
b11000110011010011110000 2
b1101010000 3
b1110111110011 4
b1110111110011 +
b1110111110011 7
b1110111110011 L
b1101010000 *
b1101010000 5
b1101010000 >
1,
#70
0,
#75
b10010010000 $
b10010010000 6
b10010010000 m
b10010010000 :
b10010010000 D
b1100110001001100000000000000 F
b10110000101110100010000 K
b10001011110000 E
b1001100011011101010111110 J
b10010000001000 #
b10010000001000 8
b10010000001000 n
b10010000001000 9
b10010000001000 R
b111101100011000000000000000 T
b11000111101110101100110111 Y
b10010011001001 S
b1101000100111100111110000 X
b1011111011000000111111111 z
b111000000001 t
b100101101110011101001110000 y
b110 0
b101100111100101100100000 2
b101101110110 3
b111110110000 4
b111110110000 +
b111110110000 7
b111110110000 L
b101101110110 *
b101101110110 5
b101101110110 >
1,
#80
0,
#85
b100000111011100000000000000 u
b100101101110011101001110000 z
b10110010000 t
b101001000110010010000000 y
b1111011000110 #
b1111011000110 8
b1111011000110 n
b1111011000110 9
b1111011000110 R
b1010000001001100000000000000 T
b1101000100111100111110000 Y
b11000010000 S
b101100100001010011101001 X
b1100010010 $
b1100010010 6
b1100010010 m
b1100010010 :
b1100010010 D
b110111001011000000000000000 F
b1001100011011101010111110 K
b10010101000010 E
b11000000100100001101100 J
b111 0
b110000001100001101100 2
b1110011100 3
b11010101101 4
b11010101101 +
b11010101101 7
b11010101101 L
b1110011100 *
b1110011100 5
b1110011100 >
1,
#90
0,
#95
b1101110010110 $
b1101110010110 6
b1101110010110 m
b1101110010110 :
b1101110010110 D
b1000001011100100000000000000 F
b11000000100100001101100 K
b11011110010100 E
b11111111101101100101111 J
b10100000010011 #
b10100000010011 8
b10100000010011 n
b10100000010011 9
b10100000010011 R
b10110001011000000000000000 T
b101100100001010011101001 Y
b1101100010111 S
b11000011101100010001111 X
b1000001110111 !
b1000001110111 \
b1000001110111 `
b1000001110111 s
b101110000100100000000000000 u
b101001000110010010000000 z
b1101110000000 t
b10111100111101111101100 y
b1000 0
b100011001010010011001 2
b10011001011 3
b1110101011 4
b1110101011 +
b1110101011 7
b1110101011 L
b10011001011 *
b10011001011 5
b10011001011 >
1,
#100
0,
#105
b1000001110111 k
b1011100001001 !
b1011100001001 \
b1011100001001 `
b1011100001001 s
b101110011001000000000000000 u
b10111100111101111101100 z
b10000010100 t
b100010100010111110000100010 y
b101100010110 #
b101100010110 8
b101100010110 n
b101100010110 9
b101100010110 R
b101110001101000000000000000 T
b11000011101100010001111 Y
b11011101110001 S
b11000001000111001110010001 X
b10000010111001 $
b10000010111001 6
b10000010111001 m
b10000010111001 :
b10000010111001 D
b1010110011000100000000000000 F
b11111111101101100101111 K
b11010011010001 E
b11110110101100101110100110 J
b1001 0
b100001011110010111100010110 2
b10010011111110 3
b1110011110101 4
b1110011110101 +
b1110011110101 7
b1110011110101 L
b10010011111110 *
b10010011111110 5
b10010011111110 >
1,
#110
0,
#115
b10101100110001 $
b10101100110001 6
b10101100110001 m
b10101100110001 :
b10101100110001 D
b1010011001110100000000000000 F
b11110110101100101110100110 K
b1010001011010 E
b1000000011110011010001111 J
b1011100011010 #
b1011100011010 8
b1011100011010 n
b1011100011010 9
b1011100011010 R
b1010110001110100000000000000 T
b11000001000111001110010001 Y
b11110001101111 S
b10000001101001110101011101 X
b1011100110010 !
b1011100110010 \
b1011100110010 `
b1011100110010 s
b1001000100100000000000000 u
b100010100010111110000100010 z
b10001111011110 t
b1011010101100001011100110 y
b1000001110111 l
b11111110001001 f
b1011100001001 k
b1010 0
b101110111111010101111011 2
b100110101011 3
b1001101110001 4
b1001101110001 +
b1001101110001 7
b1001101110001 L
b100110101011 *
b100110101011 5
b100110101011 >
1,
#120
0,
#125
b1011111010100000000000000000 g
b1011100001001 l
b1100011110111 f
b1011100110010 k
b10010001001 !
b10010001001 \
b10010001001 `
b10010001001 s
b1011000010110100000000000000 u
b1011010101100001011100110 z
b1110100011010 t
b11111001011100100111111010 y
b10101100011101 #
b10101100011101 8
b10101100011101 n
b10101100011101 9
b10101100011101 R
b1110010110011000000000000000 T
b10000001101001110101011101 Y
b1001010100011 S
b10100110011101 $
b10100110011101 6
b10100110011101 m
b10100110011101 :
b10100110011101 D
b111101010111100000000000000 F
b1000000011110011010001111 K
b10100101110001 E
1,
#130
0,
#135
b1111010101111 $
b1111010101111 6
b1111010101111 m
b1111010101111 :
b1111010101111 D
b1000110001110100000000000000 F
b100101100101 #
b100101100101 8
b100101100101 n
b100101100101 9
b100101100101 R
b101100001010100000000000000 T
b10110000101101 !
b10110000101101 \
b10110000101101 `
b10110000101101 s
b110110111111100000000000000 u
b11111001011100100111111010 z
b1011000000110 t
b111000000100001010111001001 y
b10111110101000 "
b10111110101000 Z
b10111110101000 [
b10111110101000 e
b100101011101000000000000000 g
b1011100110010 l
b100011001110 f
b10010001001 k
1,
#140
0,
#145
b1001010111010 "
b1001010111010 Z
b1001010111010 [
b1001010111010 e
b1101001101100000000000000 g
b10010001001 l
b10101101110111 f
b10110000101101 k
b1101101111111 !
b1101101111111 \
b1101101111111 `
b1101101111111 s
b1000000001110000000000000000 u
b111000000100001010111001001 z
b1101000110111 t
b1001000000100001000001011 y
b1011000010101 #
b1011000010101 8
b1011000010101 n
b1011000010101 9
b1011000010101 R
b10001100011101 $
b10001100011101 6
b10001100011101 m
b10001100011101 :
b10001100011101 D
b0 1
1,
#150
0,
#155
b10000000011100 !
b10000000011100 \
b10000000011100 `
b10000000011100 s
b1011111011001000000000000000 u
b1001000000100001000001011 z
b110111110101 t
b11000001110101111101100001 y
b11010011011 "
b11010011011 Z
b11010011011 [
b11010011011 e
b1000001001101000000000000000 g
b10110000101101 l
b1111010011 f
b1101101111111 k
b1 1
1,
#160
0,
#165
b10000010011010 "
b10000010011010 Z
b10000010011010 [
b10000010011010 e
b101101111100000000000000 g
b1101101111111 l
b11010010000001 f
b10000000011100 k
b10111110110010 !
b10111110110010 \
b10111110110010 `
b10111110110010 s
b11101111100100000000000000 u
b11000001110101111101100001 z
b1000010011111 t
b10 1
1,
#170
0,
#175
b111011111001 !
b111011111001 \
b111011111001 `
b111011111001 s
b110001001010100000000000000 u
b1011011111 "
b1011011111 Z
b1011011111 [
b1011011111 e
b1001110110001000000000000000 g
b10000000011100 l
b1111111100100 f
b10111110110010 k
b11 1
1,
#180
0,
#185
b10011101100010 "
b10011101100010 Z
b10011101100010 [
b10011101100010 e
b101111110110000000000000000 g
b10111110110010 l
b11000001001110 f
b111011111001 k
b1100010010101 !
b1100010010101 \
b1100010010101 `
b1100010010101 s
b100 1
1,
#190
0,
#195
b1011111101100 "
b1011111101100 Z
b1011111101100 [
b1011111101100 e
b1001000011110000000000000000 g
b111011111001 l
b10000100000111 f
b1100010010101 k
b101 1
1,
#200
0,
#205
b10010000111100 "
b10010000111100 Z
b10010000111100 [
b10010000111100 e
b110001100011000000000000000 g
b1100010010101 l
b1011101101011 f
b110 1
1,
#210
0,
#215
b1100011000110 "
b1100011000110 Z
b1100011000110 [
b1100011000110 e
b100011001000100000000000000 g
b111 1
1,
#220
0,
#225
b1000110010001 "
b1000110010001 Z
b1000110010001 [
b1000110010001 e
b1000 1
1,
#230
0,
#235
b1001 1
1,
#240
0,
#245
b1010 1
1,
