HDL_codes/MontgomeryReductionUnit.v
module MontgomeryReductionUnit #(
    parameter Q_WIDTH = 14,
    parameter Q = 12289,
    parameter Q_INV = 12287
)(
    input clk,
    input rst_n,

    input valid_in,
    input [Q_WIDTH-1:0] b_bar,
    input [Q_WIDTH-1:0] w_bar,

    output reg valid_out,
    output reg [Q_WIDTH-1:0] c_bar
);

    localparam R_MASK = (1 << Q_WIDTH) - 1;

    // Stage 1: Multiply
    reg [2*Q_WIDTH-1:0] x_s1;
    reg valid_s1;

    // Stage 2: Compute s
    reg [Q_WIDTH-1:0] s_s2;
    reg [2*Q_WIDTH-1:0] x_s2;
    reg valid_s2;

    // Stage 3: Compute t
    reg [2*Q_WIDTH-1:0] t_s3;
    reg valid_s3;

    always @(posedge clk or negedge rst_n) begin
        if (!rst_n) begin
            valid_s1 <= 0;
            valid_s2 <= 0;
            valid_s3 <= 0;
            valid_out <= 0;
        end else begin

            // Stage 1
            valid_s1 <= valid_in;
            if (valid_in)
                x_s1 <= b_bar * w_bar;

            // Stage 2
            valid_s2 <= valid_s1;
            if (valid_s1) begin
                s_s2 <= (x_s1 * Q_INV) & R_MASK;
                x_s2 <= x_s1;  // forward x
            end

            // Stage 3
            valid_s3 <= valid_s2;
            if (valid_s2)
                t_s3 <= x_s2 + s_s2 * Q;

            // Stage 4
            valid_out <= valid_s3;
            if (valid_s3) begin
                // shift + subtract
                if ((t_s3 >> Q_WIDTH) >= Q)
                    c_bar <= (t_s3 >> Q_WIDTH) - Q;
                else
                    c_bar <= (t_s3 >> Q_WIDTH);
            end

        end
    end

endmodule

HDL_codes/FromMont.v

module FromMontgomeryConverter #(
    parameter Q_WIDTH = 14,
    parameter Q = 12289
)(
    input clk,
    input rst_n,
    input [Q_WIDTH-1:0] c_bar,
    input valid_in,
    output wire valid_out,
    output wire [Q_WIDTH-1:0] c
);

    wire [Q_WIDTH-1:0] c_wire;

    MontgomeryReductionUnit #(
        .Q_WIDTH(Q_WIDTH),
        .Q(Q)
    ) mont_inv (
        .clk(clk),
        .rst_n(rst_n),
       .valid_in(valid_in),
        .b_bar(c_bar),
      .w_bar({{Q_WIDTH-1{1'b0}},1'b1}),
      .valid_out(valid_out),
        .c_bar(c_wire)
    );

    assign c = c_wire;

endmodule

HDL_codes/ToMont.v
module ToMontgomeryConverter #(
    parameter Q_WIDTH = 14,
    parameter Q = 12289,
  parameter R2_MOD_Q = 6829   // R^2 mod q
)(
    input clk,
    input rst_n,
    input [Q_WIDTH-1:0] a,
    input [Q_WIDTH-1:0] b,
    input valid_in,
    output wire valid_out,
    output wire [Q_WIDTH-1:0] a_bar,
    output wire [Q_WIDTH-1:0] b_bar
);

    // Wires for Montgomery outputs
    wire [Q_WIDTH-1:0] a_bar_wire;
    wire [Q_WIDTH-1:0] b_bar_wire;
    wire valid_out1;
    wire valid_out2;

    // Instantiate Montgomery Reduction Units
    MontgomeryReductionUnit #(
        .Q_WIDTH(Q_WIDTH),
        .Q(Q)
    ) mont_a (
        .clk(clk),
        .rst_n(rst_n),
        .valid_in(valid_in),
        .b_bar(a),
        .w_bar(R2_MOD_Q[Q_WIDTH-1:0]),
      .valid_out(valid_out1),
        .c_bar(a_bar_wire)
    );

    MontgomeryReductionUnit #(
        .Q_WIDTH(Q_WIDTH),
        .Q(Q)
    ) mont_b (
        .clk(clk),
        .rst_n(rst_n),
        .valid_in(valid_in),
        .b_bar(b),
        .w_bar(R2_MOD_Q[Q_WIDTH-1:0]),
      .valid_out(valid_out2),
        .c_bar(b_bar_wire)
    );
  
    assign a_bar = a_bar_wire;
    assign b_bar = b_bar_wire;
    assign valid_out=valid_out1&&valid_out2;
endmodule

verif/tb_full_montgomery_pipeline.v
module tb_full_montgomery_pipeline;

    parameter Q = 12289;
    parameter Q_WIDTH = 14;
    parameter R = (1 << Q_WIDTH);
    parameter Q_INV = 97;
    //parameter R_INV = 9216;
    parameter R2_MOD_Q = 6829;

   reg clk;
    reg rst_n;
    reg valid_in;

    reg [Q_WIDTH-1:0] a, b;

    wire [Q_WIDTH-1:0] a_bar, b_bar;
    wire [Q_WIDTH-1:0] c_bar;
    wire [Q_WIDTH-1:0] c;

    wire valid_out;
    wire valid_out1;
    wire valid_out2;

    // DUTs
    ToMontgomeryConverter form (
        .clk(clk),
        .rst_n(rst_n),
        .a(a),
        .b(b),
        .valid_in(valid_in),
        .valid_out(valid_out1),
        .a_bar(a_bar),
        .b_bar(b_bar)
    );

    MontgomeryReductionUnit mult (
        .clk(clk),
        .rst_n(rst_n),
        .valid_in(valid_out1),
        .b_bar(a_bar),
        .w_bar(b_bar),
        .valid_out(valid_out2),
        .c_bar(c_bar)
    );

    FromMontgomeryConverter inv (
        .clk(clk),
        .rst_n(rst_n),
        .valid_in(valid_out2),
        .valid_out(valid_out),
        .c_bar(c_bar),
        .c(c)
    );

    // Clock
    always #5 clk = ~clk;

    // Reference function
    function [Q_WIDTH-1:0] mod_mul;
        input [Q_WIDTH-1:0] x, y;
        reg [2*Q_WIDTH-1:0] temp;
        begin
            temp = x * y;
            mod_mul = temp % Q;
        end
    endfunction

    integer i, j;
 
    reg [Q_WIDTH-1:0] expected_q [0:9];
    reg [Q_WIDTH-1:0] a_q [0:9];
    reg [Q_WIDTH-1:0] b_q [0:9];
    initial begin
        $dumpfile("full_pipeline.vcd");
        $dumpvars(0,clk,rst_n,a,b,valid_in,a_bar,b_bar,c_bar,c,valid_out);

        clk = 0;
        rst_n = 0;
        valid_in=0;
        #20;
        rst_n = 1;
        valid_in=1;

      for (i = 0; i < 10; i = i + 1) begin
        @(posedge clk);
            a = $urandom % Q;
            b = $urandom % Q;
            expected_q[i] = mod_mul(a, b);
            a_q[i] = a;
            b_q[i] = b;
      end

        // Check outputs
        j = 0;
        while (j < 10) begin
            @(posedge clk);
            if (valid_out == 1'b1) begin
                if (expected_q[j] !== c) begin
                    $display("FAIL:");
                    $display("a=%d b=%d", a_q[j], b_q[j]);
                    $display("time=%0t, Expected=%d Got=%d",
                              $time, expected_q[j], c);
                end 
                else begin
                    $display("time=%0t, PASS: a=%d b=%d result=%d",
                              $time, a_q[j], b_q[j], c);
                end
                j = j + 1;
            end
        end

        #100;
        $finish;
    end

endmodule

verif/Mont.vcd
$date
	Sun Mar 29 14:29:06 2026
$end
$version
	Icarus Verilog
$end
$timescale
	1s
$end
$scope module tb_full_montgomery_pipeline $end
$var wire 1 ! valid_out2 $end
$var wire 1 " valid_out1 $end
$var wire 1 # valid_out $end
$var wire 14 $ c_bar [13:0] $end
$var wire 14 % c [13:0] $end
$var wire 14 & b_bar [13:0] $end
$var wire 14 ' a_bar [13:0] $end
$var parameter 32 ( Q $end
$var parameter 32 ) Q_INV $end
$var parameter 32 * Q_WIDTH $end
$var parameter 46 + R $end
$var parameter 32 , R2_MOD_Q $end
$var reg 14 - a [13:0] $end
$var reg 14 . b [13:0] $end
$var reg 1 / clk $end
$var reg 1 0 rst_n $end
$var reg 1 1 valid_in $end
$var integer 32 2 i [31:0] $end
$var integer 32 3 j [31:0] $end
$scope function mod_mul $end
$var reg 28 4 temp [27:0] $end
$var reg 14 5 x [13:0] $end
$var reg 14 6 y [13:0] $end
$upscope $end
$scope module form $end
$var wire 14 7 a [13:0] $end
$var wire 14 8 a_bar [13:0] $end
$var wire 14 9 b [13:0] $end
$var wire 14 : b_bar [13:0] $end
$var wire 1 / clk $end
$var wire 1 0 rst_n $end
$var wire 1 1 valid_in $end
$var wire 1 " valid_out $end
$var wire 1 ; valid_out2 $end
$var wire 1 < valid_out1 $end
$var wire 14 = b_bar_wire [13:0] $end
$var wire 14 > a_bar_wire [13:0] $end
$var parameter 32 ? Q $end
$var parameter 32 @ Q_WIDTH $end
$var parameter 32 A R2_MOD_Q $end
$scope module mont_a $end
$var wire 14 B b_bar [13:0] $end
$var wire 1 / clk $end
$var wire 1 0 rst_n $end
$var wire 1 1 valid_in $end
$var wire 14 C w_bar [13:0] $end
$var parameter 32 D Q $end
$var parameter 32 E Q_INV $end
$var parameter 32 F Q_WIDTH $end
$var parameter 47 G R_MASK $end
$var reg 14 H c_bar [13:0] $end
$var reg 14 I s_s2 [13:0] $end
$var reg 28 J t_s3 [27:0] $end
$var reg 1 < valid_out $end
$var reg 1 K valid_s1 $end
$var reg 1 L valid_s2 $end
$var reg 1 M valid_s3 $end
$var reg 28 N x_s1 [27:0] $end
$var reg 28 O x_s2 [27:0] $end
$upscope $end
$scope module mont_b $end
$var wire 14 P b_bar [13:0] $end
$var wire 1 / clk $end
$var wire 1 0 rst_n $end
$var wire 1 1 valid_in $end
$var wire 14 Q w_bar [13:0] $end
$var parameter 32 R Q $end
$var parameter 32 S Q_INV $end
$var parameter 32 T Q_WIDTH $end
$var parameter 47 U R_MASK $end
$var reg 14 V c_bar [13:0] $end
$var reg 14 W s_s2 [13:0] $end
$var reg 28 X t_s3 [27:0] $end
$var reg 1 ; valid_out $end
$var reg 1 Y valid_s1 $end
$var reg 1 Z valid_s2 $end
$var reg 1 [ valid_s3 $end
$var reg 28 \ x_s1 [27:0] $end
$var reg 28 ] x_s2 [27:0] $end
$upscope $end
$upscope $end
$scope module inv $end
$var wire 14 ^ c [13:0] $end
$var wire 1 / clk $end
$var wire 1 0 rst_n $end
$var wire 1 # valid_out $end
$var wire 1 ! valid_in $end
$var wire 14 _ c_wire [13:0] $end
$var wire 14 ` c_bar [13:0] $end
$var parameter 32 a Q $end
$var parameter 32 b Q_WIDTH $end
$scope module mont_inv $end
$var wire 1 / clk $end
$var wire 1 0 rst_n $end
$var wire 14 c w_bar [13:0] $end
$var wire 1 ! valid_in $end
$var wire 14 d b_bar [13:0] $end
$var parameter 32 e Q $end
$var parameter 32 f Q_INV $end
$var parameter 32 g Q_WIDTH $end
$var parameter 47 h R_MASK $end
$var reg 14 i c_bar [13:0] $end
$var reg 14 j s_s2 [13:0] $end
$var reg 28 k t_s3 [27:0] $end
$var reg 1 # valid_out $end
$var reg 1 l valid_s1 $end
$var reg 1 m valid_s2 $end
$var reg 1 n valid_s3 $end
$var reg 28 o x_s1 [27:0] $end
$var reg 28 p x_s2 [27:0] $end
$upscope $end
$upscope $end
$scope module mult $end
$var wire 14 q b_bar [13:0] $end
$var wire 1 / clk $end
$var wire 1 0 rst_n $end
$var wire 1 " valid_in $end
$var wire 14 r w_bar [13:0] $end
$var parameter 32 s Q $end
$var parameter 32 t Q_INV $end
$var parameter 32 u Q_WIDTH $end
$var parameter 47 v R_MASK $end
$var reg 14 w c_bar [13:0] $end
$var reg 14 x s_s2 [13:0] $end
$var reg 28 y t_s3 [27:0] $end
$var reg 1 ! valid_out $end
$var reg 1 z valid_s1 $end
$var reg 1 { valid_s2 $end
$var reg 1 | valid_s3 $end
$var reg 28 } x_s1 [27:0] $end
$var reg 28 ~ x_s2 [27:0] $end
$upscope $end
$upscope $end
$enddefinitions $end
$comment Show the parameter values. $end
$dumpall
b11111111111111 v
b1110 u
b10111111111111 t
b11000000000001 s
b11111111111111 h
b1110 g
b10111111111111 f
b11000000000001 e
b1110 b
b11000000000001 a
b11111111111111 U
b1110 T
b10111111111111 S
b11000000000001 R
b11111111111111 G
b1110 F
b10111111111111 E
b11000000000001 D
b1101010101101 A
b1110 @
b11000000000001 ?
b1101010101101 ,
b100000000000000 +
b1110 *
b1100001 )
b11000000000001 (
$end
#0
$dumpvars
bx ~
bx }
0|
0{
0z
bx y
bx x
bx w
bx r
bx q
bx p
bx o
0n
0m
0l
bx k
bx j
bx i
bx d
b1 c
bx `
bx _
bx ^
bx ]
bx \
0[
0Z
0Y
bx X
bx W
bx V
b1101010101101 Q
bx P
bx O
bx N
0M
0L
0K
bx J
bx I
bx H
b1101010101101 C
bx B
bx >
bx =
0<
0;
bx :
bx 9
bx 8
bx 7
bx 6
bx 5
bx 4
bx 3
bx 2
01
00
0/
bx .
bx -
bx '
bx &
bx %
bx $
0#
0"
0!
$end
#5
1/
#10
0/
#15
1/
#20
0/
b0 2
11
10
#25
b11111111101011111011001011 \
1Y
b10101110000010110011100101 N
1K
b1 2
b11111010001001010001111111 4
b1101000011001 5
b10011001010111 6
b10011001010111 .
b10011001010111 9
b10011001010111 P
b1101000011001 -
b1101000011001 7
b1101000011001 B
1/
#30
0/
#35
b10101110000010110011100101 O
b1100011011 I
1L
b1011100111100101100110000 N
b11111111101011111011001011 ]
b1000100110101 W
1Z
b10111011001100110000101010 \
b10 2
b1100001110011101011100000 4
b110111110000 5
b1110000010010 6
b1110000010010 .
b1110000010010 9
b1110000010010 P
b110111110000 -
b110111110000 7
b110111110000 B
1/
#40
0/
#45
b111001110001100000000000000 X
1[
b10111011001100110000101010 ]
b1001111010110 W
b10001011111010101110011111 \
b11010011010100000000000000 J
1M
b1011100111100101100110000 O
b11010011010000 I
b100101001010100001010110001 N
b11 2
b11101001110101101000010111 4
b10110010010101 5
b1010011111011 6
b1010011111011 .
b1010011111011 9
b1010011111011 P
b10110010010101 -
b10110010010101 7
b10110010010101 B
1/
#50
0/
#55
1"
b110100110101 '
b110100110101 8
b110100110101 q
b110100110101 >
b110100110101 H
1<
b1011010110110000000000000000 J
b100101001010100001010110001 O
b10110101001111 I
b10010000101101011111110111 N
b1110011100011 &
b1110011100011 :
b1110011100011 r
b1110011100011 =
b1110011100011 V
1;
b110101001010000000000000000 X
b10001011111010101110011111 ]
b10010001100001 W
b110001001011101111100 \
b100 2
b101000000000100000100 4
b1010110110011 5
b11101100 6
b11101100 .
b11101100 9
b11101100 P
b1010110110011 -
b1010110110011 7
b1010110110011 B
1/
#60
0/
#65
b1011111011000000111111111 }
1z
b1101010010100 &
b1101010010100 :
b1101010010100 r
b1101010010100 =
b1101010010100 V
b1001000000100000000000000000 X
b110001001011101111100 ]
b10100010000100 W
b11000111101110101100110111 \
b10110101101100 '
b10110101101100 8
b10110101101100 q
b10110101101100 >
b10110101101100 H
b1101001001000100000000000000 J
b10010000101101011111110111 O
b11100000001001 I
b10110000101110100010000 N
b101 2
b11000110011010011110000 4
b1101010000 5
b1110111110011 6
b1110111110011 .
b1110111110011 9
b1110111110011 P
b1101010000 -
b1101010000 7
b1101010000 B
1/
#70
0/
#75
b10010010000 '
b10010010000 8
b10010010000 q
b10010010000 >
b10010010000 H
b1100110001001100000000000000 J
b10110000101110100010000 O
b10001011110000 I
b1001100011011101010111110 N
b10010000001000 &
b10010000001000 :
b10010000001000 r
b10010000001000 =
b10010000001000 V
b111101100011000000000000000 X
b11000111101110101100110111 ]
b10010011001001 W
b1101000100111100111110000 \
b1011111011000000111111111 ~
b111000000001 x
1{
b100101101110011101001110000 }
b110 2
b101100111100101100100000 4
b101101110110 5
b111110110000 6
b111110110000 .
b111110110000 9
b111110110000 P
b101101110110 -
b101101110110 7
b101101110110 B
1/
#80
0/
#85
b100000111011100000000000000 y
1|
b100101101110011101001110000 ~
b10110010000 x
b101001000110010010000000 }
b1111011000110 &
b1111011000110 :
b1111011000110 r
b1111011000110 =
b1111011000110 V
b1010000001001100000000000000 X
b1101000100111100111110000 ]
b11000010000 W
b101100100001010011101001 \
b1100010010 '
b1100010010 8
b1100010010 q
b1100010010 >
b1100010010 H
b110111001011000000000000000 J
b1001100011011101010111110 O
b10010101000010 I
b11000000100100001101100 N
b111 2
b110000001100001101100 4
b1110011100 5
b11010101101 6
b11010101101 .
b11010101101 9
b11010101101 P
b1110011100 -
b1110011100 7
b1110011100 B
1/
#90
0/
#95
b1101110010110 '
b1101110010110 8
b1101110010110 q
b1101110010110 >
b1101110010110 H
b1000001011100100000000000000 J
b11000000100100001101100 O
b11011110010100 I
b11111111101101100101111 N
b10100000010011 &
b10100000010011 :
b10100000010011 r
b10100000010011 =
b10100000010011 V
b10110001011000000000000000 X
b101100100001010011101001 ]
b1101100010111 W
b11000011101100010001111 \
b1000001110111 $
b1000001110111 `
b1000001110111 d
b1000001110111 w
1!
b101110000100100000000000000 y
b101001000110010010000000 ~
b1101110000000 x
b10111100111101111101100 }
b1000 2
b100011001010010011001 4
b10011001011 5
b1110101011 6
b1110101011 .
b1110101011 9
b1110101011 P
b10011001011 -
b10011001011 7
b10011001011 B
1/
#100
0/
#105
b1000001110111 o
1l
b1011100001001 $
b1011100001001 `
b1011100001001 d
b1011100001001 w
b101110011001000000000000000 y
b10111100111101111101100 ~
b10000010100 x
b100010100010111110000100010 }
b101100010110 &
b101100010110 :
b101100010110 r
b101100010110 =
b101100010110 V
b101110001101000000000000000 X
b11000011101100010001111 ]
b11011101110001 W
b11000001000111001110010001 \
b10000010111001 '
b10000010111001 8
b10000010111001 q
b10000010111001 >
b10000010111001 H
b1010110011000100000000000000 J
b11111111101101100101111 O
b11010011010001 I
b11110110101100101110100110 N
b1001 2
b100001011110010111100010110 4
b10010011111110 5
b1110011110101 6
b1110011110101 .
b1110011110101 9
b1110011110101 P
b10010011111110 -
b10010011111110 7
b10010011111110 B
1/
#110
0/
#115
b10101100110001 '
b10101100110001 8
b10101100110001 q
b10101100110001 >
b10101100110001 H
b1010011001110100000000000000 J
b11110110101100101110100110 O
b1010001011010 I
b1000000011110011010001111 N
b1011100011010 &
b1011100011010 :
b1011100011010 r
b1011100011010 =
b1011100011010 V
b1010110001110100000000000000 X
b11000001000111001110010001 ]
b11110001101111 W
b10000001101001110101011101 \
b1011100110010 $
b1011100110010 `
b1011100110010 d
b1011100110010 w
b1001000100100000000000000 y
b100010100010111110000100010 ~
b10001111011110 x
b1011010101100001011100110 }
b1000001110111 p
b11111110001001 j
1m
b1011100001001 o
b0 3
b1010 2
b101110111111010101111011 4
b100110101011 5
b1001101110001 6
b1001101110001 .
b1001101110001 9
b1001101110001 P
b100110101011 -
b100110101011 7
b100110101011 B
1/
#120
0/
#125
b1011111010100000000000000000 k
1n
b1011100001001 p
b1100011110111 j
b1011100110010 o
b10010001001 $
b10010001001 `
b10010001001 d
b10010001001 w
b1011000010110100000000000000 y
b1011010101100001011100110 ~
b1110100011010 x
b11111001011100100111111010 }
b10101100011101 &
b10101100011101 :
b10101100011101 r
b10101100011101 =
b10101100011101 V
b1110010110011000000000000000 X
b10000001101001110101011101 ]
b1001010100011 W
b10100110011101 '
b10100110011101 8
b10100110011101 q
b10100110011101 >
b10100110011101 H
b111101010111100000000000000 J
b1000000011110011010001111 O
b10100101110001 I
1/
#130
0/
#135
b1111010101111 '
b1111010101111 8
b1111010101111 q
b1111010101111 >
b1111010101111 H
b1000110001110100000000000000 J
b100101100101 &
b100101100101 :
b100101100101 r
b100101100101 =
b100101100101 V
b101100001010100000000000000 X
b10110000101101 $
b10110000101101 `
b10110000101101 d
b10110000101101 w
b110110111111100000000000000 y
b11111001011100100111111010 ~
b1011000000110 x
b111000000100001010111001001 }
b10111110101000 %
b10111110101000 ^
b10111110101000 _
b10111110101000 i
1#
b100101011101000000000000000 k
b1011100110010 p
b100011001110 j
b10010001001 o
1/
#140
0/
#145
b1001010111010 %
b1001010111010 ^
b1001010111010 _
b1001010111010 i
b1101001101100000000000000 k
b10010001001 p
b10101101110111 j
b10110000101101 o
b1101101111111 $
b1101101111111 `
b1101101111111 d
b1101101111111 w
b1000000001110000000000000000 y
b111000000100001010111001001 ~
b1101000110111 x
b1001000000100001000001011 }
b1011000010101 &
b1011000010101 :
b1011000010101 r
b1011000010101 =
b1011000010101 V
b10001100011101 '
b10001100011101 8
b10001100011101 q
b10001100011101 >
b10001100011101 H
b1 3
1/
#150
0/
#155
b10000000011100 $
b10000000011100 `
b10000000011100 d
b10000000011100 w
b1011111011001000000000000000 y
b1001000000100001000001011 ~
b110111110101 x
b11000001110101111101100001 }
b11010011011 %
b11010011011 ^
b11010011011 _
b11010011011 i
b1000001001101000000000000000 k
b10110000101101 p
b1111010011 j
b1101101111111 o
b10 3
1/
#160
0/
#165
b10000010011010 %
b10000010011010 ^
b10000010011010 _
b10000010011010 i
b101101111100000000000000 k
b1101101111111 p
b11010010000001 j
b10000000011100 o
b10111110110010 $
b10111110110010 `
b10111110110010 d
b10111110110010 w
b11101111100100000000000000 y
b11000001110101111101100001 ~
b1000010011111 x
b11 3
1/
#170
0/
#175
b111011111001 $
b111011111001 `
b111011111001 d
b111011111001 w
b110001001010100000000000000 y
b1011011111 %
b1011011111 ^
b1011011111 _
b1011011111 i
b1001110110001000000000000000 k
b10000000011100 p
b1111111100100 j
b10111110110010 o
b100 3
1/
#180
0/
#185
b10011101100010 %
b10011101100010 ^
b10011101100010 _
b10011101100010 i
b101111110110000000000000000 k
b10111110110010 p
b11000001001110 j
b111011111001 o
b1100010010101 $
b1100010010101 `
b1100010010101 d
b1100010010101 w
b101 3
1/
#190
0/
#195
b1011111101100 %
b1011111101100 ^
b1011111101100 _
b1011111101100 i
b1001000011110000000000000000 k
b111011111001 p
b10000100000111 j
b1100010010101 o
b110 3
1/
#200
0/
#205
b10010000111100 %
b10010000111100 ^
b10010000111100 _
b10010000111100 i
b110001100011000000000000000 k
b1100010010101 p
b1011101101011 j
b111 3
1/
#210
0/
#215
b1100011000110 %
b1100011000110 ^
b1100011000110 _
b1100011000110 i
b100011001000100000000000000 k
b1000 3
1/
#220
0/
#225
b1000110010001 %
b1000110010001 ^
b1000110010001 _
b1000110010001 i
b1001 3
1/
#230
0/
#235
b1010 3
1/
